data/chic_test_region.bam
data/chic_test_region.bam.bai
data/mini_nla_test.bam
data/mini_nla_test.bam.bai
data/mini_test.bed
data/ref.fa
data/ref.fa.fai
docs/conf.py
singlecellmultiomics/__init__.py
singlecellmultiomics/version.py
singlecellmultiomics/FACS/__init__.py
singlecellmultiomics/FACS/facs.py
singlecellmultiomics/FACS/trajectory.py
singlecellmultiomics/alleleTools/__init__.py
singlecellmultiomics/alleleTools/alleleTools.py
singlecellmultiomics/alleleTools/heterozygousSNPedit.py
singlecellmultiomics/bamProcessing/__init__.py
singlecellmultiomics/bamProcessing/alignment_view.py
singlecellmultiomics/bamProcessing/bamAnalyzeCutDistances.py
singlecellmultiomics/bamProcessing/bamBinCounts.py
singlecellmultiomics/bamProcessing/bamCompare.py
singlecellmultiomics/bamProcessing/bamCopyNumber.py
singlecellmultiomics/bamProcessing/bamCountRegions.py
singlecellmultiomics/bamProcessing/bamDinucleotideDistribution.py
singlecellmultiomics/bamProcessing/bamDuprate.py
singlecellmultiomics/bamProcessing/bamExtractNearMolecules.py
singlecellmultiomics/bamProcessing/bamExtractRandomPrimerStats.py
singlecellmultiomics/bamProcessing/bamExtractSamples.py
singlecellmultiomics/bamProcessing/bamExtractVariants.py
singlecellmultiomics/bamProcessing/bamFeatureDensityVisualisation.py
singlecellmultiomics/bamProcessing/bamFeatures.py
singlecellmultiomics/bamProcessing/bamFilter.py
singlecellmultiomics/bamProcessing/bamFunctions.py
singlecellmultiomics/bamProcessing/bamMappingRate.py
singlecellmultiomics/bamProcessing/bamMatchGATKBQSRReport.py
singlecellmultiomics/bamProcessing/bamMethylationCutDistance.py
singlecellmultiomics/bamProcessing/bamMutProfiler.py
singlecellmultiomics/bamProcessing/bamOverseq.py
singlecellmultiomics/bamProcessing/bamPlateVisualisation.py
singlecellmultiomics/bamProcessing/bamPlotRTstats.py
singlecellmultiomics/bamProcessing/bamReadGroupFormat.py
singlecellmultiomics/bamProcessing/bamSetReadGroup.py
singlecellmultiomics/bamProcessing/bamSplitByTag.py
singlecellmultiomics-0.1.43.dist-info/licenses/LICENSE
singlecellmultiomics-0.1.43.dist-info/METADATA
singlecellmultiomics-0.1.43.dist-info/WHEEL
singlecellmultiomics-0.1.43.dist-info/top_level.txt
singlecellmultiomics-0.1.43.dist-info/RECORD
