Metadata-Version: 2.4
Name: singlecellmultiomics
Version: 0.1.43
Summary: Tools to deal with one or more measurements from single cells
Home-page: https://github.com/BuysDB/SingleCellMultiOmics
Download-URL: https://github.com/BuysDB/SingleCellMultiOmics/archive/v0.1.9.tar.gz
Author: Buys de Barbanson
Author-email: github@barbansonbiotech.com
License: MIT
Classifier: Development Status :: 3 - Alpha
Classifier: Intended Audience :: Science/Research
Classifier: Programming Language :: Python :: 3.6
Classifier: Programming Language :: Python :: 3.7
Classifier: License :: OSI Approved :: MIT License
License-File: LICENSE
Requires-Dist: pysam>=0.19.1
Requires-Dist: numpy>=1.16.5
Requires-Dist: pandas>=1.3.0
Requires-Dist: colorama
Requires-Dist: pyBigWig
Requires-Dist: cutadapt>=2.9
Requires-Dist: pysamiterators>=1.9
Requires-Dist: more-itertools
Requires-Dist: matplotlib
Requires-Dist: tabulate
Requires-Dist: wheel
Requires-Dist: setuptools>=40.8.0
Requires-Dist: scikit-learn>=0.21.3
Requires-Dist: seaborn>=0.11.2
Requires-Dist: statsmodels
Requires-Dist: cached_property
Requires-Dist: biopython>=1.71
Requires-Dist: pytest>=5.0.0
Requires-Dist: pytest-runner
Requires-Dist: snakemake>=5.8.1
Requires-Dist: lxml
Requires-Dist: statsmodels
Dynamic: author
Dynamic: author-email
Dynamic: classifier
Dynamic: description
Dynamic: description-content-type
Dynamic: download-url
Dynamic: home-page
Dynamic: license
Dynamic: license-file
Dynamic: requires-dist
Dynamic: summary
